sqload.py
sqload-0.1.0.dist-info/LICENSE
sqload-0.1.0.dist-info/METADATA
sqload-0.1.0.dist-info/WHEEL
sqload-0.1.0.dist-info/top_level.txt
sqload-0.1.0.dist-info/RECORD
