Metadata-Version: 2.1
Name: sqload
Version: 0.1.0
Summary: A simple utility tool that scan SQL files with queries separated by comments into python dicts.
Home-page: https://github.com/rizidoro/sqload
Author: Rafael Izidoro
Author-email: izidoro.rafa@gmail.com
License: MIT
Platform: UNKNOWN
Classifier: Development Status :: 3 - Alpha
Classifier: License :: OSI Approved :: MIT License
Classifier: Operating System :: OS Independent
Classifier: Programming Language :: Python :: 3
Classifier: Programming Language :: Python :: 3.5
Classifier: Programming Language :: Python :: 3.6
Classifier: Programming Language :: Python :: 3.7
Classifier: Programming Language :: Python :: 3.8
Classifier: Topic :: Utilities
